pyframekit/__init__.py
pyframekit/app.py
pyframekit/middleware.py
pyframekit/orm.py
pyframekit/response.py
pyframekit-0.2.0.dist-info/METADATA
pyframekit-0.2.0.dist-info/WHEEL
pyframekit-0.2.0.dist-info/top_level.txt
pyframekit-0.2.0.dist-info/RECORD
