Metadata-Version: 2.1
Name: pyframekit
Version: 0.2.0
Summary: Python Web Framework built for learning purposes.
Home-page: https://github.com/izzatkarimov/pyframekit
Author: Izzat Karimov
Author-email: izzatcodes@gmail.com
License: MIT
Platform: UNKNOWN
Classifier: License :: OSI Approved :: MIT License
Classifier: Programming Language :: Python
Classifier: Programming Language :: Python :: 3
Classifier: Programming Language :: Python :: 3.6
Classifier: Programming Language :: Python :: Implementation :: CPython
Classifier: Programming Language :: Python :: Implementation :: PyPy
Requires-Python: >=3.9.0
Requires-Dist: jinja2==3.1.5
Requires-Dist: parse==1.20.2
Requires-Dist: requests==2.32.3
Requires-Dist: requests-wsgi-adapter==0.4.1
Requires-Dist: WebOb==1.8.9
Requires-Dist: whitenoise==6.8.2
